ARS-0.5a2.dist-info/pydist.json
ARS-0.5a2.dist-info/top_level.txt
ARS-0.5a2.dist-info/DESCRIPTION.rst
ARS-0.5a2.dist-info/RECORD
ARS-0.5a2.dist-info/METADATA
ARS-0.5a2.dist-info/WHEEL
ars/constants.py
ars/__init__.py
ars/exceptions.py
ars/lib/__init__.py
ars/lib/pydispatch/saferef.py
ars/lib/pydispatch/robustapply.py
ars/lib/pydispatch/__init__.py
ars/lib/pydispatch/errors.py
ars/lib/pydispatch/dispatcher.py
ars/lib/pydispatch/robust.py
ars/lib/six/__init__.py
ars/model/__init__.py
ars/model/contrib/__init__.py
ars/model/robot/sensors.py
ars/model/robot/__init__.py
ars/model/robot/joints.py
ars/model/robot/signals.py
ars/model/simulator/__init__.py
ars/model/simulator/signals.py
ars/model/physics/base.py
ars/model/physics/ode_objects_factories.py
ars/model/physics/__init__.py
ars/model/physics/ode_adapter.py
ars/model/physics/signals.py
ars/model/geometry/__init__.py
ars/model/collision/base.py
ars/model/collision/ode_objects_factories.py
ars/model/collision/__init__.py
ars/model/collision/ode_adapter.py
ars/model/collision/signals.py
ars/graphics/base.py
ars/graphics/vtk_adapter.py
ars/graphics/__init__.py
ars/utils/geometry.py
ars/utils/mathematical.py
ars/utils/containers.py
ars/utils/generic.py
ars/utils/__init__.py
ars/utils/version.py
ars/app/__init__.py
