Metadata-Version: 2.0
Name: ARS
Version: 0.5a2
Summary: Physically-accurate robotics simulator
Home-page: http://bitbucket.org/glarrain/ars
Author: German Larrain-Munoz
Author-email: glarrain@users.noreply.github.com
License: Copyright (c) 2012, Germán Larraín Muñoz
